mff/__init__.py
mff/advanced_sampling.py
mff/calculators.py
mff/configurations.py
mff/error_measures.py
mff/gp.py
mff/utility.py
mff/interpolation/__init__.py
mff/interpolation/spline1d.py
mff/interpolation/tricube_cpp/__init__.py
mff/interpolation/tricube_cpp/_tricube.cpython-36m-darwin.so
mff/interpolation/tricube_fortran/__init__.py
mff/interpolation/tricube_fortran/_tricube.cpython-36m-darwin.so
mff/kernels/__init__.py
mff/kernels/base.py
mff/kernels/manybodykernel.py
mff/kernels/threebodykernel.py
mff/kernels/twobodykernel.py
mff/models/__init__.py
mff/models/base.py
mff/models/combined.py
mff/models/manybody.py
mff/models/threebody.py
mff/models/twobody.py
tests/__init__.py
tests/test_mff.py
mff-0.1.0.dist-info/LICENSE
mff-0.1.0.dist-info/METADATA
mff-0.1.0.dist-info/WHEEL
mff-0.1.0.dist-info/top_level.txt
mff-0.1.0.dist-info/RECORD
