Metadata-Version: 2.1
Name: mff
Version: 0.1.0
Summary: Gaussian process regression to extract non-parametric 2- and 3- body force fields.
Home-page: https://github.com/kcl-tscm/mff
Author: Claudio Zeni, Adam Fekete, Aldo Glielmo
Author-email: claudio.zeni@kcl.ac.uk
License: UNKNOWN
Platform: UNKNOWN
Classifier: Development Status :: 4 - Beta
Classifier: Programming Language :: Python :: 3
Classifier: License :: OSI Approved :: Apache Software License
Classifier: Topic :: Scientific/Engineering :: Physics
Requires-Dist: numpy
Requires-Dist: asap3
Requires-Dist: ase
Requires-Dist: theano (>=1.0.4)
Requires-Dist: scipy
